Metadata-Version: 2.1
Name: ctransformers-langdash
Version: 0.2.14
Summary: Fork of CTransformers to support Langdash functions.
Home-page: https://git.mysymphony.jp.net/nana/ctransformers
Author: Nana Mochizuki
Author-email: nana@mysymphony.jp.net
License: MIT
Keywords: ctransformers transformers ai llm
Classifier: Development Status :: 1 - Planning
Classifier: Intended Audience :: Developers
Classifier: Intended Audience :: Education
Classifier: Intended Audience :: Science/Research
Classifier: License :: OSI Approved :: MIT License
Classifier: Programming Language :: Python :: 3
Classifier: Topic :: Scientific/Engineering
Classifier: Topic :: Scientific/Engineering :: Mathematics
Classifier: Topic :: Scientific/Engineering :: Artificial Intelligence
Classifier: Topic :: Software Development
Classifier: Topic :: Software Development :: Libraries
Classifier: Topic :: Software Development :: Libraries :: Python Modules
Provides-Extra: tests
License-File: LICENSE
